zencrc/__init__.py
zencrc/crc32.py
zencrc/error_handler.py
zencrc/zencrc_cli.py
zencrc-0.9.10.dist-info/licenses/LICENSE
zencrc-0.9.10.dist-info/METADATA
zencrc-0.9.10.dist-info/WHEEL
zencrc-0.9.10.dist-info/entry_points.txt
zencrc-0.9.10.dist-info/top_level.txt
zencrc-0.9.10.dist-info/RECORD
